bids/ext/reports/__init__.py
bids/ext/reports/_version.py
bids/ext/reports/cli.py
bids/ext/reports/due.py
bids/ext/reports/logger.py
bids/ext/reports/parameters.py
bids/ext/reports/parsing.py
bids/ext/reports/report.py
bids/ext/reports/templates.py
bids/ext/reports/utils.py
bids/ext/reports/config/converters.json
bids/ext/reports/templates/.git
bids/ext/reports/templates/.gitignore
bids/ext/reports/templates/.gitmodules
bids/ext/reports/templates/.pre-commit-config.yaml
bids/ext/reports/templates/LICENSE
bids/ext/reports/templates/README.md
bids/ext/reports/templates/config/converters.json
bids/ext/reports/templates/demos/README.md
bids/ext/reports/templates/demos/data/README.md
bids/ext/reports/templates/demos/js/demo.html
bids/ext/reports/templates/demos/js/package-lock.json
bids/ext/reports/templates/demos/js/package.json
bids/ext/reports/templates/demos/js/render.js
bids/ext/reports/templates/demos/js/node_modules/.package-lock.json
bids/ext/reports/templates/demos/js/node_modules/.bin/mustache
bids/ext/reports/templates/demos/js/node_modules/mustache/CHANGELOG.md
bids/ext/reports/templates/demos/js/node_modules/mustache/LICENSE
bids/ext/reports/templates/demos/js/node_modules/mustache/README.md
bids/ext/reports/templates/demos/js/node_modules/mustache/mustache.js
bids/ext/reports/templates/demos/js/node_modules/mustache/mustache.min.js
bids/ext/reports/templates/demos/js/node_modules/mustache/mustache.mjs
bids/ext/reports/templates/demos/js/node_modules/mustache/package.json
bids/ext/reports/templates/demos/js/node_modules/mustache/bin/mustache
bids/ext/reports/templates/demos/js/node_modules/mustache/wrappers/dojo/mustache.js.post
bids/ext/reports/templates/demos/js/node_modules/mustache/wrappers/dojo/mustache.js.pre
bids/ext/reports/templates/demos/js/node_modules/mustache/wrappers/jquery/mustache.js.post
bids/ext/reports/templates/demos/js/node_modules/mustache/wrappers/jquery/mustache.js.pre
pybids_reports-0.1.0.dist-info/METADATA
pybids_reports-0.1.0.dist-info/WHEEL
pybids_reports-0.1.0.dist-info/entry_points.txt
pybids_reports-0.1.0.dist-info/licenses/LICENSE
pybids_reports-0.1.0.dist-info/RECORD
