Metadata-Version: 2.3
Name: pybids_reports
Version: 0.1.0
Summary: pybids-reports: report generator for BIDS datasets
Project-URL: Homepage, http://github.com/bids-standard/pybids-reports
Project-URL: Documentation, https://pybids-reports.readthedocs.io/en/latest/
Project-URL: Bug tracker, http://github.com/bids-standard/pybids-reports/issues
Author-email: PyBIDS Developers <bids-discussion@googlegroups.com>
Maintainer-email: PyBIDS Developers <bids-discussion@googlegroups.com>
License: MIT License
License-File: LICENSE
Classifier: Development Status :: 3 - Alpha
Classifier: Environment :: Console
Classifier: Intended Audience :: Science/Research
Classifier: License :: OSI Approved :: MIT License
Classifier: Operating System :: OS Independent
Classifier: Programming Language :: Python
Classifier: Programming Language :: Python :: 3
Classifier: Programming Language :: Python :: 3 :: Only
Classifier: Topic :: Scientific/Engineering
Requires-Python: >=3.8
Requires-Dist: chevron
Requires-Dist: nibabel
Requires-Dist: num2words
Requires-Dist: pybids>=0.15
Requires-Dist: rich
Provides-Extra: ci-tests
Requires-Dist: pybids-reports[test]; extra == 'ci-tests'
Requires-Dist: pytest-xdist; extra == 'ci-tests'
Provides-Extra: dev
Requires-Dist: pybids-reports[doc]; extra == 'dev'
Requires-Dist: pybids-reports[test]; extra == 'dev'
Provides-Extra: doc
Requires-Dist: furo; extra == 'doc'
Requires-Dist: myst-parser; extra == 'doc'
Requires-Dist: nbsphinx; extra == 'doc'
Requires-Dist: numpydoc; extra == 'doc'
Requires-Dist: sphinx; extra == 'doc'
Requires-Dist: sphinx-argparse; extra == 'doc'
Requires-Dist: sphinx-copybutton; extra == 'doc'
Requires-Dist: sphinx-gallery; extra == 'doc'
Provides-Extra: docs
Requires-Dist: pybids-reports[doc]; extra == 'docs'
Provides-Extra: test
Requires-Dist: codecov; extra == 'test'
Requires-Dist: flake8-black; extra == 'test'
Requires-Dist: flake8-docstrings; extra == 'test'
Requires-Dist: flake8-isort; extra == 'test'
Requires-Dist: pytest-cov; extra == 'test'
Requires-Dist: pytest>=3.3; extra == 'test'
Provides-Extra: tests
Requires-Dist: pybids-reports[test]; extra == 'tests'
